[
  {
    "outputFile": "Styles/Components/components.css",
    "inputFile": "Styles/Components/components.scss"
  },
  {
    "outputFile": "Styles/Themes/theme-default-dark.css",
    "inputFile": "Styles/Themes/theme-default-dark.scss"
  },
  {
    "outputFile": "Styles/Themes/theme-default-light.css",
    "inputFile": "Styles/Themes/theme-default-light.scss"
  },
  {
    "outputFile": "Styles/Themes/theme-excel-dark.css",
    "inputFile": "Styles/Themes/theme-excel-dark.scss"
  },
  {
    "outputFile": "Styles/Themes/theme-excel-light.css",
    "inputFile": "Styles/Themes/theme-excel-light.scss"
  },
  {
    "outputFile": "Styles/Themes/theme-office-dark.css",
    "inputFile": "Styles/Themes/theme-office-dark.scss"
  },
  {
    "outputFile": "Styles/Themes/theme-office-light.css",
    "inputFile": "Styles/Themes/theme-office-light.scss"
  },
  {
    "outputFile": "Styles/Themes/theme-outlook-dark.css",
    "inputFile": "Styles/Themes/theme-outlook-dark.scss"
  },
  {
    "outputFile": "Styles/Themes/theme-outlook-light.css",
    "inputFile": "Styles/Themes/theme-outlook-light.scss"
  },
  {
    "outputFile": "Styles/Themes/theme-powerapps-dark.css",
    "inputFile": "Styles/Themes/theme-powerapps-dark.scss"
  },
  {
    "outputFile": "Styles/Themes/theme-powerapps-light.css",
    "inputFile": "Styles/Themes/theme-powerapps-light.scss"
  },
  {
    "outputFile": "Styles/Themes/theme-powerbi-dark.css",
    "inputFile": "Styles/Themes/theme-powerbi-dark.scss"
  },
  {
    "outputFile": "Styles/Themes/theme-powerbi-light.css",
    "inputFile": "Styles/Themes/theme-powerbi-light.scss"
  },
  {
    "outputFile": "Styles/Themes/theme-powerpoint-dark.css",
    "inputFile": "Styles/Themes/theme-powerpoint-dark.scss"
  },
  {
    "outputFile": "Styles/Themes/theme-powerpoint-light.css",
    "inputFile": "Styles/Themes/theme-powerpoint-light.scss"
  },
  {
    "outputFile": "Styles/Themes/theme-stream-dark.css",
    "inputFile": "Styles/Themes/theme-stream-dark.scss"
  },
  {
    "outputFile": "Styles/Themes/theme-stream-light.css",
    "inputFile": "Styles/Themes/theme-stream-light.scss"
  },
  {
    "outputFile": "Styles/Themes/theme-teams-dark.css",
    "inputFile": "Styles/Themes/theme-teams-dark.scss"
  },
  {
    "outputFile": "Styles/Themes/theme-teams-light.css",
    "inputFile": "Styles/Themes/theme-teams-light.scss"
  },
  {
    "outputFile": "Styles/Themes/theme-word-dark.css",
    "inputFile": "Styles/Themes/theme-word-dark.scss"
  },
  {
    "outputFile": "Styles/Themes/theme-word-light.css",
    "inputFile": "Styles/Themes/theme-word-light.scss"
  },
  {
    "outputFile": "Styles/Themes/styles.css",
    "inputFile": "Styles/Themes/styles.scss"
  },
  {
    "outputFile": "Styles/Themes/icons.css",
    "inputFile": "Styles/Themes/icons.scss"
  },
  {
    "outputFile": "Styles/Themes/reboot.css",
    "inputFile": "Styles/Themes/reboot.scss"
  }
]